vie/__init__.py
vie/fdt.py
vie/kernelized.py
vie/nn.py
vie/rff.py
vie/util.py
vie-0.0.2.dist-info/LICENSE
vie-0.0.2.dist-info/METADATA
vie-0.0.2.dist-info/WHEEL
vie-0.0.2.dist-info/top_level.txt
vie-0.0.2.dist-info/RECORD
