Metadata-Version: 2.1
Name: vie
Version: 0.0.2
Summary: A package to estimate variable importance
Home-page: https://github.com/wdeng5120/vie
Author: Wenying Deng
Author-email: wdeng5120@gmail.com
Classifier: Programming Language :: Python :: 3
Classifier: License :: OSI Approved :: MIT License
Classifier: Operating System :: OS Independent
Requires-Python: >=3.7
License-File: LICENSE
